Verilog/Source/Design2/Design2/src/adder.v
`timescale 1 ns / 10 ps

// Jonathan Monreal

// Implements a complete adder
module adder(a, b, ci, s, co);
						 
	input a, b, ci;
	output s, co;
	wire aORb, aANDb_, aANDb, d1, d2;
	
	OAO U1(ci, a, b, a, aORb, aANDb_, co);   // Finds the carry out
	OAO U2(co_, aORb, ci, aANDb, d1, d2, s); // Finds the sum
	not #0.5 U3(co_, co);       // Inverts the carry out for use in U2
	not #0.5 U4(aANDb, aANDb_); // Inverts aANDb_ for use in U2
	
endmodule

// Implements an or-and-or arrangement
module OAO(d, e, f, g, y1, y3_, y4);
	
	input d, e, f, g;
	output y1, y3_, y4;
	wire e_, f_, y2_;
	
	not #0.5 u5(e_, e);
	not #0.5 u6(f_, f);
	nand #1 u1(y1, e_, f_);
	nand #1 u2(y2_, d, y1);
	nand #1 u3(y3_, f, g);
	nand #1 u4(y4, y2_, y3_);
	
endmodule

Verilog/Source/Design2/Design2/src/TestBench.v
`timescale 1 ns / 10 ps

module testbench();
	reg a, b, ci; // Three registers for inputs
	wire s, co;   // Three wires for outputs for and, or, and xor gates
	
	adder UUT(a, b, ci, s, co);
	
	// Initial conditions for a, b, and ci
	initial
		begin			   
			a = 0; b = 0; ci = 0;
		end
	
	// Change values of a, b, and ci at appropriate intervals
	always #40 a = ~a;
	always #20 b = ~b;
	always #10 ci = ~ci;
	
	// Display the truth table
	initial
		begin						   
			$display("                 TIME | a | b | ci | s | co");
			$monitor($time, "    %b   %b   %b    %b   %b", a, b, ci, s, co);
		end
	
	// Monitor the console and saves simulation data
	initial
		begin
			$dumpfile("adder.vcd");
			$dumpvars(1, a, b, ci, s, co);
			$dumpflush;
		end
		
	// Set test to finish after 80ms
	initial
		#80 $finish;
	
endmodule

Verilog/Source/Design2/Design2/adder.vcd
$date
	Thu Jun 25 07:24:11 2015

$end
$version
	Active-HDL 6.3
$end
$timescale
	10 ps
$end

$scope module testbench $end
$var reg	1 "	b $end
$var reg	1 #	ci $end
$var reg	1 !	a $end
$var wire	1 $	s $end
$var wire	1 %	co $end
$upscope $end

$enddefinitions $end
$dumpvars
0"
0#
0!
x%
x$
$end
#200
0%
#500
0$
#1000
1#
#1350
1$
#2000
1"
0#
#2350
0$
#2500
1$
#3000
1#
#3200
1%
#3450
0$
#4000
1!
0"
0#
#4200
0%
#4450
1$
#5000
1#
#5200
1%
#5450
0$
#6000
1"
0#
#7000
1#
#7200
1$
