Verilog/Source/design3/design3/src/flip-flops.v
module dff4(clk, reset, d, q);
	
	input clk, reset; 
	input [3:0] d;
	output reg [3:0] q;
	
	always @ (posedge clk or posedge reset)
		if (reset) q = 0;
		else q = d;
	
endmodule

Verilog/Source/Design2/Design2/src/adder.v
`timescale 1 ns / 10 ps

// Jonathan Monreal

// Implements a complete adder
module adder(a, b, ci, s, co);
						 
	input a, b, ci;
	output s, co;
	wire aORb, aANDb_, aANDb, d1, d2;
	
	OAO U1(ci, a, b, a, aORb, aANDb_, co);   // Finds the carry out
	OAO U2(co_, aORb, ci, aANDb, d1, d2, s); // Finds the sum
	not #0.5 U3(co_, co);       // Inverts the carry out for use in U2
	not #0.5 U4(aANDb, aANDb_); // Inverts aANDb_ for use in U2
	
endmodule

// Implements an or-and-or arrangement
module OAO(d, e, f, g, y1, y3_, y4);
	
	input d, e, f, g;
	output y1, y3_, y4;
	wire e_, f_, y2_;
	
	not #0.5 u5(e_, e);
	not #0.5 u6(f_, f);
	nand #1 u1(y1, e_, f_);
	nand #1 u2(y2_, d, y1);
	nand #1 u3(y3_, f, g);
	nand #1 u4(y4, y2_, y3_);
	
endmodule

Verilog/Source/design3.bak/design3/src/alu.v
module alu(A, B, CI, S0, S1, F, CO);
	
	input A, B, CI, S0, S1;
	output F, CO;
	
	adder U1(A, B ^ S0, CI & S1, F, CO);
	
endmodule

module alu4(A, B, S, F);
	
	input [3:0] A, B;
	input [1:0] S;
	output [3:0] F;
	wire CO0, CO1, CO2, CO3;
	
	alu B0(A[0], B[0], S[0], S[0], S[1], F[0], CO0);
	alu B1(A[1], B[1], CO0, S[0], S[1], F[1], CO1);
	alu B2(A[2], B[2], CO1, S[0], S[1], F[2], CO2);
	alu B3(A[3], B[3], CO2, S[0], S[1], F[3], CO3);
	
endmodule

Verilog/Source/design3/design3/src/cpu.v
module cpu4(clk, reset, s, b, a);
	
	input clk, reset;
	input [3:0] b;
	input [1:0] s;
	output [3:0] a;
	wire [3:0] f;
	
	alu4 U1(a, b, s, f);
	dff4 U2(clk, reset, f, a);
	
endmodule

Verilog/Source/design3/design3/src/TestBench.v
`timescale 1 ns / 10 ps

module TestBench;
	
	reg clk, reset;
	reg [1:0] s;
	reg [3:0] b;
	wire [3:0] a;
	
	cpu4 UUT(clk, reset, s, b, a);
	
	// Initial conditions for clk, reset, b, and s
	initial
		begin
			clk = 1; reset = 0; b = 'h0; s = 'h0;
		end
	
	always #5 clk = ~clk;
	
	// Computational tests of the cpu
	initial
		begin
	        #2 reset = 1;
			#10 reset = 0; s = 'h2; b = 'h1;
			#100 s = 'h3; b = 'h3;
			#40 s = 'h1; b = 'hE;
    	end
	
		// Monitor the console and save simulation data
	initial
		begin
			$dumpfile("cpu.vcd");
			$dumpvars(1, clk, reset, b, s, a);
			$dumpflush;
		end
		
	// Set test to finish after 80ms
	initial
		#170 $finish;
	
endmodule

Verilog/Source/design3/design3/cpu.vcd
$date
	Wed Jul 08 22:51:05 2015

$end
$version
	Active-HDL 6.3
$end
$timescale
	10 ps
$end

$scope module TestBench $end
$var reg	1 "	reset $end
$var reg	1 !	clk $end
$var reg	4 #	b[3:0] $end
$var reg	2 $	s[1:0] $end
$var wire	1 '	a[1] $end
$var wire	1 (	a[0] $end
$var wire	1 &	a[2] $end
$var wire	1 %	a[3] $end
$upscope $end

$enddefinitions $end
$dumpvars
x&
x(
b0 #
0"
1!
x'
b0 $
x%
$end
#200
1"
0%
0&
0'
0(
#500
0!
#1000
1!
#1200
0"
b10 $
b01 #
#1500
0!
#2000
1!
1(
#2500
0!
#3000
1!
1'
0(
#3500
0!
#4000
1!
1(
#4500
0!
#5000
1!
1&
0'
0(
#5500
0!
#6000
1!
1(
#6500
0!
#7000
1!
1'
0(
#7500
0!
#8000
1!
1(
#8500
0!
#9000
1!
1%
0&
0'
0(
#9500
0!
#10000
1!
1(
#10500
0!
#11000
1!
1'
0(
#11200
b11 $
b011 #
#11500
0!
#12000
1!
0%
1&
1(
#12500
0!
#13000
1!
0'
0(
#13500
0!
#14000
1!
0&
1(
#14500
0!
#15000
1!
1%
1&
1'
0(
#15200
b01 $
b1110 #
#15500
0!
#16000
1!
1(
