Verilog/Source/design4/design4/src/flip-flops.v
module dff(clk, reset, d, q);
	
	input clk, reset, d;
	output reg q;
	
	always @ (posedge clk or posedge reset)
		if (reset) q = 0;
		else q = d;
	
endmodule

Verilog/Source/design4/design4/src/parity.v
module parity(clk, reset, d, q);
	input clk, reset, d;
	output q;
	
	dff u1(clk, reset, d ^ q, q);
	
endmodule

Verilog/Source/design4/design4/src/TestBench.v
`timescale 1 ns / 10 ps

module TestBench;
	
	reg clk, reset, d;
	wire q;
	
	parity UUT(clk, reset, d, q);
	
	// Initial conditions for clk, reset, and d
	initial
		begin
			clk = 1; reset = 0; d = 0; 
		end
	
	always #5 clk = ~clk;
	
	// Computational tests of the dff
	initial
		begin
	        #2 reset = 1;
			#10 reset = 0; d = 1;
			#10 d = 0;
			#20 d = 1;
			#20	d = 0;
			#10 d = 1;
			#10 d = 0;
			#10 d = 1;
			#30 d = 0;
    	end											   
		
	// Monitor the console and save simulation data
	initial
		begin
			$dumpfile("dff.vcd");
			$dumpvars(1, clk, reset, d, q);
			$dumpflush;
		end
		
	// Set test to finish after 80ms
	initial
		#142 $finish;
		
endmodule

Verilog/Source/design4/design4/dff.vcd
$date
	Wed Jul 08 21:26:19 2015

$end
$version
	Active-HDL 6.3
$end
$timescale
	10 ps
$end

$scope module TestBench $end
$var wire	1 $	q $end
$var reg	1 !	clk $end
$var reg	1 "	reset $end
$var reg	1 #	d $end
$upscope $end

$enddefinitions $end
$dumpvars
0"
1!
0#
x$
$end
#200
1"
0$
#500
0!
#1000
1!
#1200
0"
1#
#1500
0!
#2000
1!
1$
#2200
0#
#2500
0!
#3000
1!
#3500
0!
#4000
1!
#4200
1#
#4500
0!
#5000
1!
0$
#5500
0!
#6000
1!
1$
#6200
0#
#6500
0!
#7000
1!
#7200
1#
#7500
0!
#8000
1!
0$
#8200
0#
#8500
0!
#9000
1!
#9200
1#
#9500
0!
#10000
1!
1$
#10500
0!
#11000
1!
0$
#11500
0!
#12000
1!
1$
#12200
0#
